xolo/__about__.py
xolo/__init__.py
xolo/hooks.py
xolo/iterators.py
xolo/monkey_patching.py
xolo/moving_average.py
xolo/regex.py
xolo/schemas.py
xolo/spans.py
xolo/symbols.py
xolo/tokens.py
xolo/torch.py
xolo/typing.py
xolo/utils.py
xolo-0.0.2.dist-info/METADATA
xolo-0.0.2.dist-info/WHEEL
xolo-0.0.2.dist-info/licenses/LICENSE
xolo-0.0.2.dist-info/RECORD
